{"_ts":[1556682642,1556727232,1556771723,1556815615,1556859172,1556903356,1556947235,1556992231,1557035793,1557079893,1557123829],"_r":{"breakdown":{"html":{"bytes":[407,407,407,407,407,407,407,407,407,407,407],"requests":[1,1,1,1,1,1,1,1,1,1,1]},"js":{"bytes":[0,0,0,0,0,0,0,0,0,0,0],"requests":[0,0,0,0,0,0,0,0,0,0,0]},"css":{"bytes":[0,0,0,0,0,0,0,0,0,0,0],"requests":[0,0,0,0,0,0,0,0,0,0,0]},"image":{"bytes":[0,0,0,0,0,0,0,0,0,0,0],"requests":[0,0,0,0,0,0,0,0,0,0,0]},"flash":{"bytes":[0,0,0,0,0,0,0,0,0,0,0],"requests":[0,0,0,0,0,0,0,0,0,0,0]},"font":{"bytes":[0,0,0,0,0,0,0,0,0,0,0],"requests":[0,0,0,0,0,0,0,0,0,0,0]},"video":{"bytes":[0,0,0,0,0,0,0,0,0,0,0],"requests":[0,0,0,0,0,0,0,0,0,0,0]},"other":{"bytes":[471,471,471,471,471,471,471,471,471,471,471],"requests":[2,2,2,2,2,2,2,2,2,2,2]}},"date":[1556682642,1556727232,1556771723,1556815615,1556859172,1556903356,1556947235,1556992231,1557035793,1557079893,1557123829],"domElements":[null,null,null,null,null,null,null,null,null,null,null],"domInteractive":[null,null,null,null,null,null,null,null,null,null,null],"firstPaint":[null,null,null,null,null,null,null,null,null,null,null],"fullyLoaded":[null,null,null,null,null,null,null,null,null,null,null],"id":["190501_NZ_426a15fedeeca11f103533f6fd371ee4","190501_5B_68223b37173bb2e851b053f57cdb9f8b","190502_QC_cc14c9c1410c865bf971554c3f73ab46","190502_54_877cfe923e547e93c5fa655889397611","190503_VQ_8ed911a4074bb9c059b36ed14e650b93","190503_6H_53bfdd919840813dfd87a6f2fd4cdd8e","190504_CM_812618d2645ace09719647e5ff4dea45","190504_J6_eca0573a769b623682ae56065781c9b6","190505_YW_1395048e88b5e271866fbf96209df2c9","190505_74_b467016fd6b021ecbcafba567abc1033","190506_D2_5cd7d81b055d4bd235cdda2392d1c7ae"],"loadTime":[null,null,null,null,null,null,null,null,null,null,null],"render":[null,null,null,null,null,null,null,null,null,null,null],"SpeedIndex":[null,null,null,null,null,null,null,null,null,null,null],"TTFB":[null,null,null,null,null,null,null,null,null,null,null],"videoFrames":[[{"_i":"ms_000000.jpg","_t":0,"_vc":100}],[{"_i":"ms_000000.jpg","_t":0,"_vc":100}],[{"_i":"ms_000000.jpg","_t":0,"_vc":100}],[{"_i":"ms_000000.jpg","_t":0,"_vc":100}],[{"_i":"ms_000000.jpg","_t":0,"_vc":100}],[{"_i":"ms_000000.jpg","_t":0,"_vc":100}],[{"_i":"ms_000000.jpg","_t":0,"_vc":100}],[{"_i":"ms_000000.jpg","_t":0,"_vc":100}],[{"_i":"ms_000000.jpg","_t":0,"_vc":100}],[{"_i":"ms_000000.jpg","_t":0,"_vc":100}],[{"_i":"ms_000000.jpg","_t":0,"_vc":100}]],"visualComplete":[null,null,null,null,null,null,null,null,null,null,null],"lighthouse":[null,null,null,null,null,null,null,null,null,null,null],"pagespeed":[96,96,96,96,95,96,96,96,96,96,96]}}