{"_ts":[1538376245],"_r":{"breakdown":{"html":{"bytes":[28923],"requests":[18]},"js":{"bytes":[1004889],"requests":[47]},"css":{"bytes":[61907],"requests":[5]},"image":{"bytes":[1402670],"requests":[38]},"flash":{"bytes":[0],"requests":[0]},"font":{"bytes":[14252],"requests":[1]},"video":{"bytes":[0],"requests":[0]},"other":{"bytes":[4330],"requests":[11]}},"date":[1538376245],"domElements":[1553],"domInteractive":[10335],"firstPaint":[11216.50000001],"fullyLoaded":[50683],"id":["181001_6V_ca38e9fa8b44762b75365b0bcf275858"],"loadTime":[46641],"render":[11200],"SpeedIndex":[12428],"TTFB":[5202],"videoFrames":[[{"_i":"ms_000000.jpg","_t":0,"_vc":0},{"_i":"ms_011200.jpg","_t":11200,"_vc":75},{"_i":"ms_011400.jpg","_t":11400,"_vc":75},{"_i":"ms_011500.jpg","_t":11500,"_vc":90},{"_i":"ms_011600.jpg","_t":11600,"_vc":99},{"_i":"ms_011700.jpg","_t":11700,"_vc":99},{"_i":"ms_016300.jpg","_t":16300,"_vc":98},{"_i":"ms_018400.jpg","_t":18400,"_vc":99},{"_i":"ms_020200.jpg","_t":20200,"_vc":96},{"_i":"ms_020500.jpg","_t":20500,"_vc":96},{"_i":"ms_021000.jpg","_t":21000,"_vc":97},{"_i":"ms_021100.jpg","_t":21100,"_vc":99},{"_i":"ms_021200.jpg","_t":21200,"_vc":99},{"_i":"ms_021500.jpg","_t":21500,"_vc":97},{"_i":"ms_021700.jpg","_t":21700,"_vc":97},{"_i":"ms_022000.jpg","_t":22000,"_vc":97},{"_i":"ms_022200.jpg","_t":22200,"_vc":97},{"_i":"ms_022500.jpg","_t":22500,"_vc":97},{"_i":"ms_022800.jpg","_t":22800,"_vc":97},{"_i":"ms_023200.jpg","_t":23200,"_vc":97},{"_i":"ms_023500.jpg","_t":23500,"_vc":97},{"_i":"ms_024300.jpg","_t":24300,"_vc":97},{"_i":"ms_024500.jpg","_t":24500,"_vc":97},{"_i":"ms_025000.jpg","_t":25000,"_vc":97},{"_i":"ms_026300.jpg","_t":26300,"_vc":96},{"_i":"ms_027100.jpg","_t":27100,"_vc":98},{"_i":"ms_027200.jpg","_t":27200,"_vc":99},{"_i":"ms_027300.jpg","_t":27300,"_vc":96},{"_i":"ms_029300.jpg","_t":29300,"_vc":96},{"_i":"ms_029800.jpg","_t":29800,"_vc":96},{"_i":"ms_031300.jpg","_t":31300,"_vc":97},{"_i":"ms_031501.jpg","_t":31501,"_vc":97},{"_i":"ms_031800.jpg","_t":31800,"_vc":97},{"_i":"ms_036300.jpg","_t":36300,"_vc":96},{"_i":"ms_041300.jpg","_t":41300,"_vc":97},{"_i":"ms_046300.jpg","_t":46300,"_vc":96},{"_i":"ms_046900.jpg","_t":46900,"_vc":96},{"_i":"ms_047100.jpg","_t":47100,"_vc":96},{"_i":"ms_047400.jpg","_t":47400,"_vc":96},{"_i":"ms_047600.jpg","_t":47600,"_vc":96},{"_i":"ms_047900.jpg","_t":47900,"_vc":96},{"_i":"ms_048400.jpg","_t":48400,"_vc":96},{"_i":"ms_048600.jpg","_t":48600,"_vc":96},{"_i":"ms_049100.jpg","_t":49100,"_vc":96},{"_i":"ms_049800.jpg","_t":49800,"_vc":97},{"_i":"ms_049900.jpg","_t":49900,"_vc":98},{"_i":"ms_050000.jpg","_t":50000,"_vc":99},{"_i":"ms_051300.jpg","_t":51300,"_vc":100}]],"visualComplete":[51300],"lighthouse":[23],"pagespeed":[71]}}