{"_ts":[1554079370,1554124265],"_r":{"breakdown":{"html":{"bytes":[48990,48990],"requests":[2,2]},"js":{"bytes":[370285,363413],"requests":[15,15]},"css":{"bytes":[128998,128998],"requests":[3,3]},"image":{"bytes":[82690,82690],"requests":[34,34]},"flash":{"bytes":[0,0],"requests":[0,0]},"font":{"bytes":[221384,221384],"requests":[9,9]},"video":{"bytes":[0,0],"requests":[0,0]},"other":{"bytes":[47,47],"requests":[3,3]}},"date":[1554079370,1554124265],"domElements":[282,282],"domInteractive":[6591,6426],"firstPaint":[5767.4199999965,5634.2999999979],"fullyLoaded":[12683,12209],"id":["190401_Q9_35e7d1078b4d952ea804d5f3ec505d69","190401_BE_716f8a7045b4be0ac5a7d2fd9ea796d0"],"loadTime":[11392,11109],"render":[5800,5700],"SpeedIndex":[5868,5767],"TTFB":[3447,3145],"videoFrames":[[{"_i":"ms_000000.jpg","_t":0,"_vc":0},{"_i":"ms_005800.jpg","_t":5800,"_vc":98},{"_i":"ms_006500.jpg","_t":6500,"_vc":97},{"_i":"ms_006600.jpg","_t":6600,"_vc":97},{"_i":"ms_006700.jpg","_t":6700,"_vc":98},{"_i":"ms_006800.jpg","_t":6800,"_vc":99},{"_i":"ms_007200.jpg","_t":7200,"_vc":99},{"_i":"ms_007500.jpg","_t":7500,"_vc":99},{"_i":"ms_008300.jpg","_t":8300,"_vc":99},{"_i":"ms_008500.jpg","_t":8500,"_vc":99},{"_i":"ms_008800.jpg","_t":8800,"_vc":98},{"_i":"ms_008900.jpg","_t":8900,"_vc":99},{"_i":"ms_009000.jpg","_t":9000,"_vc":99},{"_i":"ms_009500.jpg","_t":9500,"_vc":99},{"_i":"ms_009800.jpg","_t":9800,"_vc":99},{"_i":"ms_010300.jpg","_t":10300,"_vc":99},{"_i":"ms_010501.jpg","_t":10501,"_vc":99},{"_i":"ms_011100.jpg","_t":11100,"_vc":99},{"_i":"ms_011200.jpg","_t":11200,"_vc":99},{"_i":"ms_011300.jpg","_t":11300,"_vc":100}],[{"_i":"ms_000000.jpg","_t":0,"_vc":0},{"_i":"ms_005700.jpg","_t":5700,"_vc":98},{"_i":"ms_006700.jpg","_t":6700,"_vc":99},{"_i":"ms_007000.jpg","_t":7000,"_vc":99},{"_i":"ms_007200.jpg","_t":7200,"_vc":99},{"_i":"ms_007500.jpg","_t":7500,"_vc":99},{"_i":"ms_008100.jpg","_t":8100,"_vc":98},{"_i":"ms_008200.jpg","_t":8200,"_vc":98},{"_i":"ms_008300.jpg","_t":8300,"_vc":98},{"_i":"ms_008500.jpg","_t":8500,"_vc":99},{"_i":"ms_008700.jpg","_t":8700,"_vc":99},{"_i":"ms_008800.jpg","_t":8800,"_vc":99},{"_i":"ms_009000.jpg","_t":9000,"_vc":99},{"_i":"ms_009300.jpg","_t":9300,"_vc":99},{"_i":"ms_009500.jpg","_t":9500,"_vc":99},{"_i":"ms_010000.jpg","_t":10000,"_vc":99},{"_i":"ms_010301.jpg","_t":10301,"_vc":99},{"_i":"ms_010900.jpg","_t":10900,"_vc":99},{"_i":"ms_011000.jpg","_t":11000,"_vc":100}]],"visualComplete":[11300,11000],"lighthouse":[50,23],"pagespeed":[78,78]}}