{"_ts":[1575162376],"_r":{"breakdown":{"html":{"bytes":[33110],"requests":[9]},"js":{"bytes":[1473990],"requests":[34]},"css":{"bytes":[117193],"requests":[10]},"image":{"bytes":[1203943],"requests":[56]},"flash":{"bytes":[0],"requests":[0]},"font":{"bytes":[225956],"requests":[7]},"video":{"bytes":[0],"requests":[0]},"other":{"bytes":[4134],"requests":[28]}},"date":[1575162376],"domElements":[1356],"domInteractive":[7004],"firstPaint":[3668.8949999989],"fullyLoaded":[11292],"id":["191201_XF_a96f50c31891c08f7f3fcd5cfa0552ea"],"loadTime":[9067],"render":[3700],"SpeedIndex":[6831],"TTFB":[2323],"videoFrames":[[{"_i":"ms_000000.jpg","_t":0,"_vc":0},{"_i":"ms_003700.jpg","_t":3700,"_vc":3},{"_i":"ms_003800.jpg","_t":3800,"_vc":6},{"_i":"ms_004200.jpg","_t":4200,"_vc":19},{"_i":"ms_004300.jpg","_t":4300,"_vc":7},{"_i":"ms_004400.jpg","_t":4400,"_vc":13},{"_i":"ms_004500.jpg","_t":4500,"_vc":13},{"_i":"ms_004600.jpg","_t":4600,"_vc":14},{"_i":"ms_004700.jpg","_t":4700,"_vc":14},{"_i":"ms_004800.jpg","_t":4800,"_vc":19},{"_i":"ms_005000.jpg","_t":5000,"_vc":19},{"_i":"ms_005100.jpg","_t":5100,"_vc":19},{"_i":"ms_005200.jpg","_t":5200,"_vc":19},{"_i":"ms_005300.jpg","_t":5300,"_vc":22},{"_i":"ms_005900.jpg","_t":5900,"_vc":22},{"_i":"ms_007300.jpg","_t":7300,"_vc":22},{"_i":"ms_007500.jpg","_t":7500,"_vc":83},{"_i":"ms_007600.jpg","_t":7600,"_vc":100}]],"visualComplete":[7600],"lighthouse":[12],"pagespeed":[78]}}