{"_ts":[1527822666,1527866368],"_r":{"breakdown":{"html":{"bytes":[37941,43755],"requests":[19,19]},"js":{"bytes":[692396,702348],"requests":[24,26]},"css":{"bytes":[75343,75278],"requests":[8,8]},"image":{"bytes":[1347722,1347602],"requests":[84,84]},"flash":{"bytes":[0,0],"requests":[0,0]},"font":{"bytes":[146237,146272],"requests":[4,4]},"video":{"bytes":[0,0],"requests":[0,0]},"other":{"bytes":[3767,3680],"requests":[32,30]}},"date":[1527822666,1527866368],"domElements":[1361,1361],"domInteractive":[14223,14408],"firstPaint":[13571.3,13772.399999994],"fullyLoaded":[34645,33943],"id":["180601_08_7cdb35f645baf75f24f46ca3f9da848d","180601_57_c75edd28502ead6448c54c97aba670b3"],"loadTime":[24329,23614],"render":[13600,13800],"SpeedIndex":[24645,24783],"TTFB":[7019,5769],"videoFrames":[[{"_i":"ms_000000.jpg","_t":0,"_vc":0},{"_i":"ms_013600.jpg","_t":13600,"_vc":6},{"_i":"ms_013900.jpg","_t":13900,"_vc":6},{"_i":"ms_014000.jpg","_t":14000,"_vc":6},{"_i":"ms_014100.jpg","_t":14100,"_vc":6},{"_i":"ms_014200.jpg","_t":14200,"_vc":6},{"_i":"ms_014600.jpg","_t":14600,"_vc":6},{"_i":"ms_014700.jpg","_t":14700,"_vc":3},{"_i":"ms_014800.jpg","_t":14800,"_vc":27},{"_i":"ms_016200.jpg","_t":16200,"_vc":41},{"_i":"ms_016600.jpg","_t":16600,"_vc":39},{"_i":"ms_016700.jpg","_t":16700,"_vc":39},{"_i":"ms_017100.jpg","_t":17100,"_vc":39},{"_i":"ms_017300.jpg","_t":17300,"_vc":39},{"_i":"ms_018100.jpg","_t":18100,"_vc":39},{"_i":"ms_018300.jpg","_t":18300,"_vc":39},{"_i":"ms_018800.jpg","_t":18800,"_vc":39},{"_i":"ms_019100.jpg","_t":19100,"_vc":39},{"_i":"ms_019900.jpg","_t":19900,"_vc":39},{"_i":"ms_020000.jpg","_t":20000,"_vc":40},{"_i":"ms_020500.jpg","_t":20500,"_vc":58},{"_i":"ms_021100.jpg","_t":21100,"_vc":52},{"_i":"ms_021800.jpg","_t":21800,"_vc":52},{"_i":"ms_022300.jpg","_t":22300,"_vc":52},{"_i":"ms_022900.jpg","_t":22900,"_vc":52},{"_i":"ms_023400.jpg","_t":23400,"_vc":52},{"_i":"ms_023600.jpg","_t":23600,"_vc":52},{"_i":"ms_024100.jpg","_t":24100,"_vc":52},{"_i":"ms_024600.jpg","_t":24600,"_vc":52},{"_i":"ms_026300.jpg","_t":26300,"_vc":54},{"_i":"ms_026500.jpg","_t":26500,"_vc":42},{"_i":"ms_027000.jpg","_t":27000,"_vc":48},{"_i":"ms_032400.jpg","_t":32400,"_vc":47},{"_i":"ms_032500.jpg","_t":32500,"_vc":51},{"_i":"ms_033000.jpg","_t":33000,"_vc":92},{"_i":"ms_033500.jpg","_t":33500,"_vc":99},{"_i":"ms_034100.jpg","_t":34100,"_vc":100}],[{"_i":"ms_000000.jpg","_t":0,"_vc":0},{"_i":"ms_013800.jpg","_t":13800,"_vc":6},{"_i":"ms_013900.jpg","_t":13900,"_vc":6},{"_i":"ms_014100.jpg","_t":14100,"_vc":6},{"_i":"ms_014200.jpg","_t":14200,"_vc":3},{"_i":"ms_014300.jpg","_t":14300,"_vc":3},{"_i":"ms_014400.jpg","_t":14400,"_vc":3},{"_i":"ms_015100.jpg","_t":15100,"_vc":27},{"_i":"ms_015600.jpg","_t":15600,"_vc":41},{"_i":"ms_016100.jpg","_t":16100,"_vc":39},{"_i":"ms_016300.jpg","_t":16300,"_vc":39},{"_i":"ms_016500.jpg","_t":16500,"_vc":39},{"_i":"ms_016600.jpg","_t":16600,"_vc":39},{"_i":"ms_017200.jpg","_t":17200,"_vc":39},{"_i":"ms_018300.jpg","_t":18300,"_vc":39},{"_i":"ms_019100.jpg","_t":19100,"_vc":39},{"_i":"ms_019600.jpg","_t":19600,"_vc":39},{"_i":"ms_019700.jpg","_t":19700,"_vc":39},{"_i":"ms_019800.jpg","_t":19800,"_vc":39},{"_i":"ms_020200.jpg","_t":20200,"_vc":39},{"_i":"ms_020500.jpg","_t":20500,"_vc":48},{"_i":"ms_021000.jpg","_t":21000,"_vc":50},{"_i":"ms_021600.jpg","_t":21600,"_vc":52},{"_i":"ms_022200.jpg","_t":22200,"_vc":52},{"_i":"ms_022900.jpg","_t":22900,"_vc":52},{"_i":"ms_023400.jpg","_t":23400,"_vc":52},{"_i":"ms_023900.jpg","_t":23900,"_vc":52},{"_i":"ms_024000.jpg","_t":24000,"_vc":51},{"_i":"ms_026300.jpg","_t":26300,"_vc":52},{"_i":"ms_026500.jpg","_t":26500,"_vc":44},{"_i":"ms_027000.jpg","_t":27000,"_vc":48},{"_i":"ms_031800.jpg","_t":31800,"_vc":48},{"_i":"ms_032300.jpg","_t":32300,"_vc":48},{"_i":"ms_032500.jpg","_t":32500,"_vc":50},{"_i":"ms_033000.jpg","_t":33000,"_vc":87},{"_i":"ms_033500.jpg","_t":33500,"_vc":100}]],"visualComplete":[34100,33500],"lighthouse":[36,36],"pagespeed":[52,51]}}