{"_ts":[1535767511],"_r":{"breakdown":{"html":{"bytes":[80305],"requests":[20]},"js":{"bytes":[1307124],"requests":[77]},"css":{"bytes":[125177],"requests":[23]},"image":{"bytes":[2751599],"requests":[92]},"flash":{"bytes":[0],"requests":[0]},"font":{"bytes":[134707],"requests":[7]},"video":{"bytes":[8317729],"requests":[1]},"other":{"bytes":[418424],"requests":[4]}},"date":[1535767511],"domElements":[2071],"domInteractive":[4704],"firstPaint":[2959.2000000048],"fullyLoaded":[14769],"id":["180901_AY_a1badfcf6c1ecb24d5661081ef1cd61b"],"loadTime":[12444],"render":[3200],"SpeedIndex":[9978],"TTFB":[1141],"videoFrames":[[{"_i":"ms_000000.jpg","_t":0,"_vc":0},{"_i":"ms_003200.jpg","_t":3200,"_vc":6},{"_i":"ms_003400.jpg","_t":3400,"_vc":7},{"_i":"ms_003500.jpg","_t":3500,"_vc":7},{"_i":"ms_003600.jpg","_t":3600,"_vc":7},{"_i":"ms_003700.jpg","_t":3700,"_vc":7},{"_i":"ms_003900.jpg","_t":3900,"_vc":8},{"_i":"ms_004200.jpg","_t":4200,"_vc":10},{"_i":"ms_004500.jpg","_t":4500,"_vc":10},{"_i":"ms_006400.jpg","_t":6400,"_vc":11},{"_i":"ms_007400.jpg","_t":7400,"_vc":16},{"_i":"ms_007500.jpg","_t":7500,"_vc":16},{"_i":"ms_007600.jpg","_t":7600,"_vc":15},{"_i":"ms_007700.jpg","_t":7700,"_vc":15},{"_i":"ms_007800.jpg","_t":7800,"_vc":15},{"_i":"ms_007900.jpg","_t":7900,"_vc":15},{"_i":"ms_008000.jpg","_t":8000,"_vc":15},{"_i":"ms_008100.jpg","_t":8100,"_vc":15},{"_i":"ms_008200.jpg","_t":8200,"_vc":26},{"_i":"ms_008300.jpg","_t":8300,"_vc":26},{"_i":"ms_008500.jpg","_t":8500,"_vc":37},{"_i":"ms_009100.jpg","_t":9100,"_vc":37},{"_i":"ms_009500.jpg","_t":9500,"_vc":37},{"_i":"ms_010000.jpg","_t":10000,"_vc":37},{"_i":"ms_010600.jpg","_t":10600,"_vc":65},{"_i":"ms_012400.jpg","_t":12400,"_vc":65},{"_i":"ms_012500.jpg","_t":12500,"_vc":94},{"_i":"ms_013000.jpg","_t":13000,"_vc":96},{"_i":"ms_013500.jpg","_t":13500,"_vc":96},{"_i":"ms_014400.jpg","_t":14400,"_vc":99},{"_i":"ms_014500.jpg","_t":14500,"_vc":99},{"_i":"ms_014900.jpg","_t":14900,"_vc":100}]],"visualComplete":[14900],"lighthouse":[31],"pagespeed":[59]}}