{"_ts":[1561961472],"_r":{"breakdown":{"html":{"bytes":[49304],"requests":[17]},"js":{"bytes":[1444459],"requests":[54]},"css":{"bytes":[19731],"requests":[3]},"image":{"bytes":[1662499],"requests":[87]},"flash":{"bytes":[0],"requests":[0]},"font":{"bytes":[32584],"requests":[2]},"video":{"bytes":[2050921],"requests":[1]},"other":{"bytes":[46162],"requests":[27]}},"date":[1561961472],"domElements":[1706],"domInteractive":[3876],"firstPaint":[3565.8399999957],"fullyLoaded":[43151],"id":["190701_69_823420a01c1957e558fc9f3a1ac696fb"],"loadTime":[23047],"render":[3600],"SpeedIndex":[7403],"TTFB":[2017],"videoFrames":[[{"_i":"ms_000000.jpg","_t":0,"_vc":0},{"_i":"ms_003600.jpg","_t":3600,"_vc":24},{"_i":"ms_003800.jpg","_t":3800,"_vc":32},{"_i":"ms_003900.jpg","_t":3900,"_vc":33},{"_i":"ms_004400.jpg","_t":4400,"_vc":33},{"_i":"ms_004500.jpg","_t":4500,"_vc":33},{"_i":"ms_004600.jpg","_t":4600,"_vc":33},{"_i":"ms_004700.jpg","_t":4700,"_vc":32},{"_i":"ms_005400.jpg","_t":5400,"_vc":78},{"_i":"ms_006100.jpg","_t":6100,"_vc":93},{"_i":"ms_006300.jpg","_t":6300,"_vc":93},{"_i":"ms_009600.jpg","_t":9600,"_vc":91},{"_i":"ms_010100.jpg","_t":10100,"_vc":92},{"_i":"ms_010200.jpg","_t":10200,"_vc":93},{"_i":"ms_010300.jpg","_t":10300,"_vc":93},{"_i":"ms_015200.jpg","_t":15200,"_vc":91},{"_i":"ms_015700.jpg","_t":15700,"_vc":91},{"_i":"ms_016400.jpg","_t":16400,"_vc":91},{"_i":"ms_016700.jpg","_t":16700,"_vc":91},{"_i":"ms_016900.jpg","_t":16900,"_vc":91},{"_i":"ms_017400.jpg","_t":17400,"_vc":91},{"_i":"ms_018000.jpg","_t":18000,"_vc":92},{"_i":"ms_018100.jpg","_t":18100,"_vc":93},{"_i":"ms_018200.jpg","_t":18200,"_vc":91},{"_i":"ms_018700.jpg","_t":18700,"_vc":91},{"_i":"ms_019200.jpg","_t":19200,"_vc":92},{"_i":"ms_019300.jpg","_t":19300,"_vc":93},{"_i":"ms_019400.jpg","_t":19400,"_vc":93},{"_i":"ms_019900.jpg","_t":19900,"_vc":91},{"_i":"ms_020200.jpg","_t":20200,"_vc":91},{"_i":"ms_020400.jpg","_t":20400,"_vc":91},{"_i":"ms_021500.jpg","_t":21500,"_vc":91},{"_i":"ms_022000.jpg","_t":22000,"_vc":91},{"_i":"ms_022600.jpg","_t":22600,"_vc":92},{"_i":"ms_022700.jpg","_t":22700,"_vc":93},{"_i":"ms_022800.jpg","_t":22800,"_vc":91},{"_i":"ms_023300.jpg","_t":23300,"_vc":92},{"_i":"ms_023400.jpg","_t":23400,"_vc":93},{"_i":"ms_023500.jpg","_t":23500,"_vc":93},{"_i":"ms_026200.jpg","_t":26200,"_vc":91},{"_i":"ms_026600.jpg","_t":26600,"_vc":92},{"_i":"ms_026700.jpg","_t":26700,"_vc":92},{"_i":"ms_026800.jpg","_t":26800,"_vc":93},{"_i":"ms_037600.jpg","_t":37600,"_vc":83},{"_i":"ms_037700.jpg","_t":37700,"_vc":100},{"_i":"ms_041100.jpg","_t":41100,"_vc":97},{"_i":"ms_041300.jpg","_t":41300,"_vc":97},{"_i":"ms_042000.jpg","_t":42000,"_vc":98},{"_i":"ms_042100.jpg","_t":42100,"_vc":98},{"_i":"ms_042200.jpg","_t":42200,"_vc":100}]],"visualComplete":[37700],"lighthouse":[30],"pagespeed":[63]}}