{"_ts":[1530423016],"_r":{"breakdown":{"html":{"bytes":[49882],"requests":[30]},"js":{"bytes":[1404781],"requests":[43]},"css":{"bytes":[105995],"requests":[8]},"image":{"bytes":[1284412],"requests":[112]},"flash":{"bytes":[0],"requests":[0]},"font":{"bytes":[65770],"requests":[5]},"video":{"bytes":[0],"requests":[0]},"other":{"bytes":[4804],"requests":[46]}},"date":[1530423016],"domElements":[1379],"domInteractive":[12598],"firstPaint":[11626.300000004],"fullyLoaded":[37778],"id":["180701_9Y_97324e300c43d07cb6b34c1a0e8b0c8e"],"loadTime":[27516],"render":[11700],"SpeedIndex":[23612],"TTFB":[4917],"videoFrames":[[{"_i":"ms_000000.jpg","_t":0,"_vc":0},{"_i":"ms_011700.jpg","_t":11700,"_vc":2},{"_i":"ms_011800.jpg","_t":11800,"_vc":3},{"_i":"ms_011900.jpg","_t":11900,"_vc":4},{"_i":"ms_012000.jpg","_t":12000,"_vc":4},{"_i":"ms_012100.jpg","_t":12100,"_vc":4},{"_i":"ms_012200.jpg","_t":12200,"_vc":4},{"_i":"ms_012300.jpg","_t":12300,"_vc":4},{"_i":"ms_012500.jpg","_t":12500,"_vc":3},{"_i":"ms_012600.jpg","_t":12600,"_vc":2},{"_i":"ms_013400.jpg","_t":13400,"_vc":10},{"_i":"ms_013600.jpg","_t":13600,"_vc":8},{"_i":"ms_013800.jpg","_t":13800,"_vc":96},{"_i":"ms_014200.jpg","_t":14200,"_vc":97},{"_i":"ms_015700.jpg","_t":15700,"_vc":97},{"_i":"ms_016400.jpg","_t":16400,"_vc":97},{"_i":"ms_017200.jpg","_t":17200,"_vc":97},{"_i":"ms_017300.jpg","_t":17300,"_vc":97},{"_i":"ms_017400.jpg","_t":17400,"_vc":97},{"_i":"ms_017700.jpg","_t":17700,"_vc":97},{"_i":"ms_018200.jpg","_t":18200,"_vc":97},{"_i":"ms_018600.jpg","_t":18600,"_vc":98},{"_i":"ms_019000.jpg","_t":19000,"_vc":50},{"_i":"ms_019500.jpg","_t":19500,"_vc":38},{"_i":"ms_023500.jpg","_t":23500,"_vc":38},{"_i":"ms_024000.jpg","_t":24000,"_vc":38},{"_i":"ms_024500.jpg","_t":24500,"_vc":38},{"_i":"ms_025400.jpg","_t":25400,"_vc":38},{"_i":"ms_025800.jpg","_t":25800,"_vc":38},{"_i":"ms_026000.jpg","_t":26000,"_vc":38},{"_i":"ms_026500.jpg","_t":26500,"_vc":74},{"_i":"ms_027000.jpg","_t":27000,"_vc":65},{"_i":"ms_027900.jpg","_t":27900,"_vc":65},{"_i":"ms_028000.jpg","_t":28000,"_vc":65},{"_i":"ms_032300.jpg","_t":32300,"_vc":68},{"_i":"ms_032500.jpg","_t":32500,"_vc":72},{"_i":"ms_033000.jpg","_t":33000,"_vc":49},{"_i":"ms_033700.jpg","_t":33700,"_vc":48},{"_i":"ms_034400.jpg","_t":34400,"_vc":48},{"_i":"ms_034700.jpg","_t":34700,"_vc":48},{"_i":"ms_035200.jpg","_t":35200,"_vc":48},{"_i":"ms_038300.jpg","_t":38300,"_vc":48},{"_i":"ms_038500.jpg","_t":38500,"_vc":73},{"_i":"ms_038900.jpg","_t":38900,"_vc":100}]],"visualComplete":[38900],"lighthouse":[23],"pagespeed":[46]}}