{"_ts":[1514805279],"_r":{"breakdown":{"html":{"bytes":[47369],"requests":[17]},"js":{"bytes":[833614],"requests":[32]},"css":{"bytes":[124148],"requests":[7]},"image":{"bytes":[2425322],"requests":[95]},"flash":{"bytes":[0],"requests":[0]},"font":{"bytes":[98890],"requests":[3]},"video":{"bytes":[0],"requests":[0]},"other":{"bytes":[2004],"requests":[3]}},"date":[1514805279],"domElements":[1595],"domInteractive":[6365],"firstPaint":[3716],"fullyLoaded":[11351],"id":["180101_7B_698114bef61d461157a834e65b750c09"],"loadTime":[10236],"render":[3886],"SpeedIndex":[9284],"TTFB":[2184],"videoFrames":[[{"_i":"frame_0000.jpg","_t":0,"_vc":0},{"_i":"frame_0039.jpg","_t":3900,"_vc":0},{"_i":"frame_0041.jpg","_t":4100,"_vc":0},{"_i":"frame_0042.jpg","_t":4200,"_vc":0},{"_i":"frame_0044.jpg","_t":4400,"_vc":0},{"_i":"frame_0045.jpg","_t":4500,"_vc":0},{"_i":"frame_0046.jpg","_t":4600,"_vc":0},{"_i":"frame_0048.jpg","_t":4800,"_vc":0},{"_i":"frame_0049.jpg","_t":4900,"_vc":0},{"_i":"frame_0050.jpg","_t":5000,"_vc":0},{"_i":"frame_0052.jpg","_t":5200,"_vc":0},{"_i":"frame_0053.jpg","_t":5300,"_vc":0},{"_i":"frame_0054.jpg","_t":5400,"_vc":0},{"_i":"frame_0056.jpg","_t":5600,"_vc":0},{"_i":"frame_0057.jpg","_t":5700,"_vc":0},{"_i":"frame_0059.jpg","_t":5900,"_vc":0},{"_i":"frame_0060.jpg","_t":6000,"_vc":0},{"_i":"frame_0062.jpg","_t":6200,"_vc":0},{"_i":"frame_0064.jpg","_t":6400,"_vc":0},{"_i":"frame_0065.jpg","_t":6500,"_vc":0},{"_i":"frame_0067.jpg","_t":6700,"_vc":0},{"_i":"frame_0069.jpg","_t":6900,"_vc":0},{"_i":"frame_0070.jpg","_t":7000,"_vc":0},{"_i":"frame_0072.jpg","_t":7200,"_vc":68},{"_i":"frame_0077.jpg","_t":7700,"_vc":70},{"_i":"frame_0085.jpg","_t":8500,"_vc":84},{"_i":"frame_0089.jpg","_t":8900,"_vc":55},{"_i":"frame_0125.jpg","_t":12500,"_vc":100}]],"visualComplete":[12500],"lighthouse":[null],"pagespeed":[39]}}